{
    "sourceFile": "src/components/forms/ResetEmail.jsx",
    "activeCommit": 0,
    "commits": [
        {
            "activePatchIndex": 3,
            "patches": [
                {
                    "date": 1752560824953,
                    "content": "Index: \n===================================================================\n--- \n+++ \n"
                },
                {
                    "date": 1752560910054,
                    "content": "Index: \n===================================================================\n--- \n+++ \n@@ -6,9 +6,9 @@\n     <div className=\"min-h-screen flex items-center justify-center bg-gray-100 p-6\">\r\n       <div className=\"bg-white shadow-lg rounded-lg w-full max-w-4xl flex flex-col md:flex-row\">\r\n         \r\n         {/* Left image */}\r\n-        <div className=\"w-full md:w-1/2 relative\">\r\n+        <div className=\"w-full md:w-1/2 relative \">\r\n           <img\r\n             src=\"rectangle-780.png\"\r\n             alt=\"Signup Visual\"\r\n             className=\"w-full h-full object-cover rounded-t-lg md:rounded-l-lg md:rounded-tr-none\"\r\n"
                },
                {
                    "date": 1752560919158,
                    "content": "Index: \n===================================================================\n--- \n+++ \n@@ -6,9 +6,9 @@\n     <div className=\"min-h-screen flex items-center justify-center bg-gray-100 p-6\">\r\n       <div className=\"bg-white shadow-lg rounded-lg w-full max-w-4xl flex flex-col md:flex-row\">\r\n         \r\n         {/* Left image */}\r\n-        <div className=\"w-full md:w-1/2 relative mt-14\">\r\n+        <div className=\"w-full md:w-1/2 relative \">\r\n           <img\r\n             src=\"rectangle-780.png\"\r\n             alt=\"Signup Visual\"\r\n             className=\"w-full h-full object-cover rounded-t-lg md:rounded-l-lg md:rounded-tr-none\"\r\n"
                },
                {
                    "date": 1752561195990,
                    "content": "Index: \n===================================================================\n--- \n+++ \n@@ -0,0 +1,53 @@\n+import React from \"react\";\r\n+import { Link } from \"react-router-dom\";\r\n+\r\n+const ResetEmailSent = () => {\r\n+  return (\r\n+    <div className=\"min-h-screen flex items-center justify-center bg-gray-100 p-6\">\r\n+      <div className=\"bg-white shadow-lg rounded-lg w-full max-w-4xl flex flex-col md:flex-row\">\r\n+        \r\n+        {/* Left image */}\r\n+        <div className=\"w-full md:w-1/2 relative \">\r\n+          <img\r\n+            src=\"rectangle-780.png\"\r\n+            alt=\"Signup Visual\"\r\n+            className=\"w-full h-full object-cover rounded-t-lg md:rounded-l-lg md:rounded-tr-none\"\r\n+          />\r\n+          <img\r\n+            src=\"logo copy.svg\"\r\n+            alt=\"West Brook Logo\"\r\n+            className=\"absolute top-1/2 left-1/2 transform -translate-x-1/2 -translate-y-1/2 max-w-[150px] sm:max-w-[200px] lg:max-w-[250px] max-h-[200px] sm:max-h-[300px] lg:max-h-[500px] w-full h-auto animate-bounce-once\"\r\n+          />\r\n+        </div>\r\n+\r\n+        {/* Right content */}\r\n+        <div className=\"w-full md:w-1/2 p-8 mt-14\">\r\n+          {/* Heading */}\r\n+          <div className=\"mb-6\">\r\n+            <h2 className=\"text-2xl font-semibold mb-3\">Check Your Email</h2>\r\n+            <p className=\"text-sm text-gray-700 leading-relaxed\">\r\n+              We’ll send an email to{\" \"}\r\n+              <span className=\"font-medium text-black\">james@gmail.com</span>, if it’s associated with your account.\r\n+              <br />\r\n+              <br />\r\n+              Bear in mind it will be valid for <strong>30 minutes only</strong>.\r\n+            </p>\r\n+          </div>\r\n+\r\n+          {/* Go back to login */}\r\n+          <div className=\"text-sm text-center text-gray-600\">\r\n+            Go back to{\" \"}\r\n+            <Link\r\n+              to=\"/loginform\"\r\n+              className=\"text-[#005e0e] font-medium hover:underline\"\r\n+            >\r\n+              LOGIN\r\n+            </Link>\r\n+          </div>\r\n+        </div>\r\n+      </div>\r\n+    </div>\r\n+  );\r\n+};\r\n+\r\n+export default ResetEmailSent;\r\n"
                }
            ],
            "date": 1752560824953,
            "name": "Commit-0",
            "content": "import React from \"react\";\r\nimport { Link } from \"react-router-dom\";\r\n\r\nconst ResetEmailSent = () => {\r\n  return (\r\n    <div className=\"min-h-screen flex items-center justify-center bg-gray-100 p-6\">\r\n      <div className=\"bg-white shadow-lg rounded-lg w-full max-w-4xl flex flex-col md:flex-row\">\r\n        \r\n        {/* Left image */}\r\n        <div className=\"w-full md:w-1/2 relative\">\r\n          <img\r\n            src=\"rectangle-780.png\"\r\n            alt=\"Signup Visual\"\r\n            className=\"w-full h-full object-cover rounded-t-lg md:rounded-l-lg md:rounded-tr-none\"\r\n          />\r\n          <img\r\n            src=\"logo copy.svg\"\r\n            alt=\"West Brook Logo\"\r\n            className=\"absolute top-1/2 left-1/2 transform -translate-x-1/2 -translate-y-1/2 max-w-[150px] sm:max-w-[200px] lg:max-w-[250px] max-h-[200px] sm:max-h-[300px] lg:max-h-[500px] w-full h-auto animate-bounce-once\"\r\n          />\r\n        </div>\r\n\r\n        {/* Right content */}\r\n        <div className=\"w-full md:w-1/2 p-8\">\r\n          {/* Heading */}\r\n          <div className=\"mb-6\">\r\n            <h2 className=\"text-2xl font-semibold mb-3\">Check Your Email</h2>\r\n            <p className=\"text-sm text-gray-700 leading-relaxed\">\r\n              We’ll send an email to{\" \"}\r\n              <span className=\"font-medium text-black\">james@gmail.com</span>, if it’s associated with your account.\r\n              <br />\r\n              <br />\r\n              Bear in mind it will be valid for <strong>30 minutes only</strong>.\r\n            </p>\r\n          </div>\r\n\r\n          {/* Go back to login */}\r\n          <div className=\"text-sm text-center text-gray-600\">\r\n            Go back to{\" \"}\r\n            <Link\r\n              to=\"/login\"\r\n              className=\"text-[#005e0e] font-medium hover:underline\"\r\n            >\r\n              LOGIN\r\n            </Link>\r\n          </div>\r\n        </div>\r\n      </div>\r\n    </div>\r\n  );\r\n};\r\n\r\nexport default ResetEmailSent;\r\n"
        }
    ]
}